{"template":"__react_static_root__/src/content/club/Page","sharedHashesByProp":{},"data":{"site":{"name":"Mason High School","directory":"mhs","coordinator":{"title":"Student Activities Director","name":"Lorri Allen","email":"AllenL@masonohioschools.com"}},"page":{"timestamp":"2022-07-31T19:30:05.818Z","editorEmail":"mhsrockclimbing@masonohioschools.com","name":"MHS Rock Climbing","category":"Sports, Involvement","schoologyPage":"https://masonohioschools.schoology.com/group/6013267144","website":"https://sites.google.com/view/mhsrockclimbing/home?authuser=0","description":"The Mason Rock Climbing club introduces students to the unique but challenging sport of Rock Climbing. The club will meet twice a month at Mosaic Climbing, where they members explore the various types of climbing: bouldering, which is a powerful and ropeless form of climbing, toprope, which is an endurance/distance based form of climbing, and speed. Climbers will work in group orientated settings where they collaborate together to crack tough climbs and push their limits!","mobilityRating":"High","soundRating":"Medium","advisorName":"TJ Wilson","advisorEmail":"wilsonth@masonohioschools.com","additionalName":"Navjot Singh","additionalEmail":"navjot.singh84@masonohioschools.com","additionalTitle":"Club Leader","thumbURL":"https://drive.google.com/open?id=1egOrGvucbR4ytY5WrvIme0t2YpiZs7f5","additionalContent":"No","sectionOneTitle":"","sectionOneContent":"","sectionTwoTitle":"","sectionTwoContent":"","sectionThreeTitle":"","sectionThreeContent":"","fileExtension":"png"}},"path":"mhs/mhs-rock-climbing"}
