{"template":"__react_static_root__/src/content/club/Page","sharedHashesByProp":{},"data":{"site":{"name":"Mason High School","directory":"mhs","coordinator":{"title":"Student Activities Assistant Director","name":"Lori Howard","email":"HowardL@masonohioschools.com"}},"page":{"timestamp":"2023-08-14T14:46:33.370Z","editorEmail":"schnellj@masonohioschools.com","name":"Tabletop Gaming Club","category":"Gaming","schoologyPage":"https://masonohioschools.schoology.com/group/839425875","description":"This club meets once a week after school to play tabletop games.  This can include board games, card games, roleplaying games, Dungeons & Dragons, etc.  The club has a large library of games, or you are free to bring in your own.  Please contact Mr. Schnell (room A313) with any questions!","mobilityRating":"Low","soundRating":"Medium","advisorName":"Mr. Schnell","advisorEmail":"schnellj@masonohioschools.com","additionalName":"","additionalEmail":"","additionalTitle":"","thumbURL":"https://drive.google.com/open?id=1GCS6-1Tz1KJ3XnCSmdP5KL_BpSawOScx","additionalContent":"No","sectionOneTitle":"","sectionOneContent":"","sectionTwoTitle":"","sectionTwoContent":"","sectionThreeTitle":"","sectionThreeContent":"","fileExtension":"jpeg"}},"path":"mhs/tabletop-gaming-club"}
